LICENSE
MANIFEST.in
README.md
README.rst
setup.py
test-import-mysql.py
test.py
BayesRedis/__init__.c
bayesredis.egg-info/PKG-INFO
bayesredis.egg-info/SOURCES.txt
bayesredis.egg-info/dependency_links.txt
bayesredis.egg-info/not-zip-safe
bayesredis.egg-info/top_level.txt