Metadata-Version: 1.0
Name: bayesredis
Version: 1.2.0
Summary: A Simple Naive Bayes Classifier in Python
Home-page: https://github.com/tistaharahap/python-bayes-redis
Author: Batista Harahap
Author-email: batista@bango29.com
License: MIT
Keywords: bayes naive classifier redis cython machine learning
Platform: UNKNOWN
